antools/__init__.py
antools/__main__.py
antools/automation_template/bin/example_script.bat
antools/automation_template/ci_cd/github_actions.yml
antools/automation_template/config/config.yaml
antools/automation_template/data/sample_data.csv
antools/automation_template/docker/Dockerfile
antools/automation_template/docs/API_documentation.md
antools/automation_template/logs/app.log
antools/automation_template/migrations/migration.sql
antools/automation_template/models/model.pkl
antools/automation_template/notebooks/example_notebook.ipynb
antools/automation_template/scripts/deploy.bat
antools/automation_template/src/main.py
antools/automation_template/tests/test_main.py
antools/code_to_sort/helpers/__init__.py
antools/code_to_sort/helpers/_approach_comparator_class.py
antools/code_to_sort/helpers/_examples/_example_approach_comparator.py
antools/code_to_sort/logging/__init__.py
antools/code_to_sort/logging/_examples/_example_logger.py
antools/code_to_sort/logging/_logger_class.py
antools/code_to_sort/multiprocessing/__init__.py
antools/code_to_sort/multiprocessing/_examples/_example_mp_handler.py
antools/code_to_sort/multiprocessing/_examples/_example_mp_process_class.py
antools/code_to_sort/multiprocessing/_mp_handler.py
antools/code_to_sort/multiprocessing/_mp_process_class.py
antools/code_to_sort/pybase_windows-master/.gitignore
antools/code_to_sort/pybase_windows-master/app_builder.py
antools/code_to_sort/pybase_windows-master/app_code/antools/base/_logger.py
antools/code_to_sort/pybase_windows-master/app_constants.py
antools/code_to_sort/pybase_windows-master/app_settings.py
antools/code_to_sort/pybase_windows-master/DEV_README.md
antools/code_to_sort/pybase_windows-master/dev_test_file.py
antools/code_to_sort/pybase_windows-master/icon.ico
antools/code_to_sort/pybase_windows-master/LICENSE
antools/code_to_sort/pybase_windows-master/main.py
antools/code_to_sort/pybase_windows-master/poetry.lock
antools/code_to_sort/pybase_windows-master/pyproject.toml
antools-2025.8.8.dist-info/LICENSE
antools-2025.8.8.dist-info/METADATA
antools-2025.8.8.dist-info/WHEEL
antools-2025.8.8.dist-info/RECORD
